odoo/addons/tms_account_asset/README.rst
odoo/addons/tms_account_asset/__init__.py
odoo/addons/tms_account_asset/__manifest__.py
odoo/addons/tms_account_asset/i18n/tms_account_asset.pot
odoo/addons/tms_account_asset/models/__init__.py
odoo/addons/tms_account_asset/models/account_asset.py
odoo/addons/tms_account_asset/models/account_asset_profile.py
odoo/addons/tms_account_asset/models/account_move.py
odoo/addons/tms_account_asset/models/fleet_vehicle.py
odoo/addons/tms_account_asset/models/fleet_vehicle_model_category.py
odoo/addons/tms_account_asset/readme/CONFIGURE.md
odoo/addons/tms_account_asset/readme/CONTRIBUTORS.md
odoo/addons/tms_account_asset/readme/CREDITS.md
odoo/addons/tms_account_asset/readme/DESCRIPTION.md
odoo/addons/tms_account_asset/readme/INSTALL.md
odoo/addons/tms_account_asset/readme/MAINTAINERS.md
odoo/addons/tms_account_asset/readme/USAGE.md
odoo/addons/tms_account_asset/static/description/icon.png
odoo/addons/tms_account_asset/static/description/icon.svg
odoo/addons/tms_account_asset/static/description/index.html
odoo/addons/tms_account_asset/views/account_asset_profile_views.xml
odoo/addons/tms_account_asset/views/account_asset_views.xml
odoo/addons/tms_account_asset/views/fleet_vehicle_model_category_views.xml
odoo/addons/tms_account_asset/views/fleet_vehicle_views.xml
odoo_addon_tms_account_asset-17.0.1.0.0.2.dist-info/METADATA
odoo_addon_tms_account_asset-17.0.1.0.0.2.dist-info/WHEEL
odoo_addon_tms_account_asset-17.0.1.0.0.2.dist-info/top_level.txt
odoo_addon_tms_account_asset-17.0.1.0.0.2.dist-info/RECORD
